[
  {
    "line": 2,
    "elements": [
      {
        "before": [
          {
            "result": {
              "duration": 5810908250,
              "status": "passed"
            },
            "match": {
              "location": "TechGlobalSteps.setup()"
            }
          },
          {
            "result": {
              "duration": 657791,
              "status": "passed"
            },
            "match": {
              "location": "WikipediaSteps.setup()"
            }
          },
          {
            "result": {
              "duration": 27125,
              "status": "passed"
            },
            "match": {
              "location": "BaseSteps.setup()"
            }
          },
          {
            "result": {
              "duration": 324833,
              "status": "passed"
            },
            "match": {
              "location": "GoogleSteps.setup()"
            }
          }
        ],
        "line": 5,
        "name": "Validate Google Search",
        "description": "",
        "id": "google-search-functionality;validate-google-search",
        "after": [
          {
            "result": {
              "duration": 116143958,
              "status": "passed"
            },
            "match": {
              "location": "Hooks.teardown(Scenario)"
            }
          }
        ],
        "type": "scenario",
        "keyword": "Scenario",
        "steps": [
          {
            "result": {
              "duration": 6712636958,
              "status": "passed"
            },
            "line": 6,
            "name": "user navigates to \"https://www.google.com/\"",
            "match": {
              "arguments": [
                {
                  "val": "\"https://www.google.com/\"",
                  "offset": 18
                }
              ],
              "location": "BaseSteps.userNavigatesTo(String)"
            },
            "keyword": "Given "
          },
          {
            "result": {
              "duration": 9034201417,
              "status": "passed"
            },
            "line": 7,
            "name": "user search for \"Tesla\"",
            "match": {
              "arguments": [
                {
                  "val": "\"Tesla\"",
                  "offset": 16
                }
              ],
              "location": "GoogleSteps.user_search_for(String)"
            },
            "keyword": "When "
          },
          {
            "result": {
              "duration": 18773167,
              "status": "passed"
            },
            "line": 8,
            "name": "user should see \"Tesla\" in the url",
            "match": {
              "arguments": [
                {
                  "val": "\"Tesla\"",
                  "offset": 16
                }
              ],
              "location": "BaseSteps.user_should_see_in_the_url(String)"
            },
            "keyword": "Then "
          },
          {
            "result": {
              "duration": 24775708,
              "status": "passed"
            },
            "line": 9,
            "name": "user should see \"Tesla\" in the title",
            "match": {
              "arguments": [
                {
                  "val": "\"Tesla\"",
                  "offset": 16
                }
              ],
              "location": "BaseSteps.user_should_see_in_the_title(String)"
            },
            "keyword": "And "
          }
        ],
        "tags": [
          {
            "name": "@Regression"
          },
          {
            "name": "@Integration"
          }
        ]
      },
      {
        "before": [
          {
            "result": {
              "duration": 4772680125,
              "status": "passed"
            },
            "match": {
              "location": "TechGlobalSteps.setup()"
            }
          },
          {
            "result": {
              "duration": 1567917,
              "status": "passed"
            },
            "match": {
              "location": "WikipediaSteps.setup()"
            }
          },
          {
            "result": {
              "duration": 20667,
              "status": "passed"
            },
            "match": {
              "location": "BaseSteps.setup()"
            }
          },
          {
            "result": {
              "duration": 157917,
              "status": "passed"
            },
            "match": {
              "location": "GoogleSteps.setup()"
            }
          }
        ],
        "line": 12,
        "name": "Validate Google Search results",
        "description": "",
        "id": "google-search-functionality;validate-google-search-results",
        "after": [
          {
            "result": {
              "duration": 117834000,
              "status": "passed"
            },
            "match": {
              "location": "Hooks.teardown(Scenario)"
            }
          }
        ],
        "type": "scenario",
        "keyword": "Scenario",
        "steps": [
          {
            "result": {
              "duration": 6495844375,
              "status": "passed"
            },
            "line": 13,
            "name": "user navigates to \"https://www.google.com/\"",
            "match": {
              "arguments": [
                {
                  "val": "\"https://www.google.com/\"",
                  "offset": 18
                }
              ],
              "location": "BaseSteps.userNavigatesTo(String)"
            },
            "keyword": "Given "
          },
          {
            "result": {
              "duration": 16431127875,
              "status": "passed"
            },
            "line": 14,
            "name": "user search for \"Apple\"",
            "match": {
              "arguments": [
                {
                  "val": "\"Apple\"",
                  "offset": 16
                }
              ],
              "location": "GoogleSteps.user_search_for(String)"
            },
            "keyword": "When "
          },
          {
            "result": {
              "duration": 51596000,
              "status": "passed"
            },
            "line": 15,
            "name": "user should see results are more than 0",
            "match": {
              "arguments": [
                {
                  "val": "0",
                  "offset": 38
                }
              ],
              "location": "GoogleSteps.userShouldSeeResultsAreMoreThan(int)"
            },
            "keyword": "Then "
          }
        ],
        "tags": [
          {
            "name": "@Regression"
          },
          {
            "name": "@Sanity"
          }
        ]
      }
    ],
    "name": "Google Search Functionality",
    "description": "",
    "id": "google-search-functionality",
    "keyword": "Feature",
    "uri": "src/test/resources/features/google.feature",
    "tags": [
      {
        "name": "@Regression",
        "type": "Tag",
        "location": {
          "line": 1,
          "column": 1
        }
      }
    ]
  }
]